{"Numar Matricol": "CTI024504", "Nume": "Cernătescu", "Prenume": ["Flaviu", "Carol", "Antim"], "CNP": "5020419453633", "Serie Buletin": "B4", "Numar Buletin": 512766, "Adresa": {"Oras": "Sighetu Marmației", "Strada": "Strada Ion Creangă", "Numar": 29, "Bloc": 3, "Apartament": 28}, "BuletinEliberat": "SPCLEP Gorj", "NumeTata": "Mierlescu Eugen Mihăiță ", "NumeMama": "Amuntencei Tincuța Florina Cerasela ", "Data Nastere": {"Zi": 19, "Luna": 4, "An": 2002}, "Data Inmatriculare": {"Zi": 2, "Luna": 2, "An": 2024}, "MediaBAC": 9.08, "MedieMatematica": 6.91, "MedieFizica": 8.0, "MedieInformatica": 8.19, "Competente": {"OralRomana": "B2", "Digitale": "A2", "LimbaMaterna": "B2", "LingvisticeEngleza_Franceza": {"IntelegereTextAudiat": "A2", "IntelegereTextCitit": "B2", "MesajeScrise": "B2", "MesajeOrale": "A2", "InteractiuneOrala": "B2"}}, "Medie_generala_liceu": 9.19, "NumeLiceu": "Colegiul Național Spiru Haret", "RecomandareMedic": "apt", "Data_eliberare_adeverinta_medicala": {"Zi": 18, "Luna": 2, "An": 2024}, "Suma_insccriere_achitata": "100", "Data_achitare": {"Zi": 2, "Luna": 2, "An": 2024}, "Scutit de taxa": "false", "Alta_licenta": "false", "Student_Alta_Facultate": "true", "Absolvire_liceu_inainte_an_curent": "true", "Categorii_speciale": "false", "Program_studii_alta_limba": "true", "Cale_poza": "D:\\PYTHON\\Generare_Studenti_Local\\imagini\\B7.jpg"}