{"Numar Matricol": "CTI024898", "Nume": "Duiculescu", "Prenume": ["Mugur"], "CNP": "5031222032661", "Serie Buletin": "SJ", "Numar Buletin": 383219, "Adresa": {"Oras": "Râmnicu Vâlcea", "Strada": "Strada Tudor Vladimirescu", "Numar": 3, "Bloc": 18, "Apartament": 18}, "BuletinEliberat": "SPCLEP Galați", "NumeTata": "Junate Cedrin Beniamin Eustațiu Moise ", "NumeMama": "Ambăruș Natalia Robertina Casiana ", "Data Nastere": {"Zi": 22, "Luna": 12, "An": 2003}, "Data Inmatriculare": {"Zi": 2, "Luna": 2, "An": 2024}, "MediaBAC": 6.02, "MedieMatematica": 7.83, "MedieFizica": 7.31, "MedieInformatica": 8.49, "Competente": {"OralRomana": "B1", "Digitale": "B2", "LimbaMaterna": "B2", "LingvisticeEngleza_Franceza": {"IntelegereTextAudiat": "A2", "IntelegereTextCitit": "B1", "MesajeScrise": "B2", "MesajeOrale": "B2", "InteractiuneOrala": "A2"}}, "Medie_generala_liceu": 6.34, "NumeLiceu": "Colegiul Național Tudor Vianu", "RecomandareMedic": "apt", "Data_eliberare_adeverinta_medicala": {"Zi": 11, "Luna": 2, "An": 2024}, "Suma_insccriere_achitata": "100", "Data_achitare": {"Zi": 2, "Luna": 2, "An": 2024}, "Scutit de taxa": "true", "Alta_licenta": "true", "Student_Alta_Facultate": "true", "Absolvire_liceu_inainte_an_curent": "false", "Categorii_speciale": "true", "Program_studii_alta_limba": "false", "Cale_poza": "D:\\PYTHON\\Generare_Studenti_Local\\imagini\\B4.jpg"}