{"Numar Matricol": "CTI024117", "Nume": "Onila", "Prenume": "Cristina Janeta Heracleea ", "CNP": "6061229045758", "Serie Buletin": "CJ", "Numar Prenume": 119029, "Adresa": {"Oras": "Deva", "Strada": "Strada Avram Iancu", "Numar": 25, "Bloc": 11, "Apartament": 29}, "BuletinEliberat": "SPCLEP Arad", "NumeTata": "Vulpeș Nichifor Daniel ", "NumeMama": "Mazilescu Lenuța Georgia Robertina Stana Ștefania ", "Data Nastere": {"Zi": 29, "Luna": 12, "An": 2006}, "Data Inmatriculare": {"Zi": 2, "Luna": 2, "An": 2024}, "MediaBAC": 8.4, "MedieMatematica": 9.83, "MedieFizica": 7.31, "MedieInformatica": 8.24, "Competente": {"OralRomana": "B1", "Digitale": "A2", "LimbaMaterna": "B1", "LingvisticeEngleza_Franceza": {"IntelegereTextAudiat": "B1", "IntelegereTextCitit": "B2", "MesajeScrise": "A2", "MesajeOrale": "B1", "InteractiuneOrala": "B2"}}, "Medie_generala_liceu": 8.05, "NumeLiceu": "Colegiul Național Mircea cel Bătrân", "RecomandareMedic": "apt", "Data_eliberare_adeverinta_medicala": {"Zi": 17, "Luna": 2, "An": 2024}, "Suma_insccriere_achitata": "100", "Data_achitare": {"Zi": 2, "Luna": 2, "An": 2024}, "Scutit de taxa": "false", "Alta_licenta": "true", "Student_Alta_Facultate": "true", "Absolvire_liceu_inainte_an_curent": "false", "Categorii_speciale": "true", "Program_studii_alta_limba": "false", "Cale_poza": "D:\\PYTHON\\Generare_Studenti_Local\\imagini\\F1.jpg"}