{"Numar Matricol": "CTI024338", "Nume": "Ternăvean", "Prenume": ["Rareș", "Cristea", "Bernard", "Iacob"], "CNP": "5001101484297", "Serie Buletin": "TR", "Numar Buletin": 519947, "Adresa": {"Oras": "Miercurea Ciuc", "Strada": "Strada Ion Creangă", "Numar": 18, "Bloc": 1, "Apartament": 32}, "BuletinEliberat": "SPCLEP Galați", "NumeTata": "Ioanid Mitică Inocențiu Traian Viorel ", "NumeMama": "Stoenete Izaura Stanca Floarea Viorela Sanda ", "Data Nastere": {"Zi": 1, "Luna": 11, "An": 2000}, "Data Inmatriculare": {"Zi": 3, "Luna": 2, "An": 2024}, "MediaBAC": 8.79, "MedieMatematica": 9.77, "MedieFizica": 9.25, "MedieInformatica": 7.65, "Competente": {"OralRomana": "B1", "Digitale": "B2", "LimbaMaterna": "B1", "LingvisticeEngleza_Franceza": {"IntelegereTextAudiat": "A2", "IntelegereTextCitit": "B1", "MesajeScrise": "A2", "MesajeOrale": "A2", "InteractiuneOrala": "B2"}}, "Medie_generala_liceu": 9.08, "NumeLiceu": "Colegiul Național Tudor Vianu", "RecomandareMedic": "inapt", "Data_eliberare_adeverinta_medicala": {"Zi": 24, "Luna": 2, "An": 2024}, "Suma_insccriere_achitata": "100", "Data_achitare": {"Zi": 3, "Luna": 2, "An": 2024}, "Scutit de taxa": "true", "Alta_licenta": "true", "Student_Alta_Facultate": "false", "Absolvire_liceu_inainte_an_curent": "true", "Categorii_speciale": "false", "Program_studii_alta_limba": "true", "Cale_poza": "D:\\PYTHON\\Generare_Studenti_Local\\imagini\\B2.jpg"}